polymorphic_tree/MANIFEST.in
polymorphic_tree/README.rst
polymorphic_tree/__init__.py
polymorphic_tree/managers.py
polymorphic_tree/models.py
polymorphic_tree/setup.py
polymorphic_tree/__pycache__/__init__.cpython-38.pyc
polymorphic_tree/__pycache__/managers.cpython-38.pyc
polymorphic_tree/__pycache__/models.cpython-38.pyc
polymorphic_tree/admin/__init__.py
polymorphic_tree/admin/childadmin.py
polymorphic_tree/admin/parentadmin.py
polymorphic_tree/admin/__pycache__/__init__.cpython-38.pyc
polymorphic_tree/admin/__pycache__/childadmin.cpython-38.pyc
polymorphic_tree/admin/__pycache__/parentadmin.cpython-38.pyc
polymorphic_tree/locale/es_AR/LC_MESSAGES/django.po
polymorphic_tree/locale/nl/LC_MESSAGES/django.po
polymorphic_tree/static/polymorphic_tree/jquery.cookie.js
polymorphic_tree/static/polymorphic_tree/adminlist/arrow-down.gif
polymorphic_tree/static/polymorphic_tree/adminlist/arrow-up.gif
polymorphic_tree/static/polymorphic_tree/adminlist/nav-bg.gif
polymorphic_tree/static/polymorphic_tree/adminlist/nodetree.css
polymorphic_tree/static/polymorphic_tree/adminlist/nodetree_classic.css
polymorphic_tree/static/polymorphic_tree/adminlist/nodetree_flat.css
polymorphic_tree/static/polymorphic_tree/adminlist/nodetree_grappelli.css
polymorphic_tree/static/polymorphic_tree/adminlist/zebra-flat.png
polymorphic_tree/static/polymorphic_tree/adminlist/zebra-grappelli.png
polymorphic_tree/static/polymorphic_tree/adminlist/zebra.png
polymorphic_tree/static/polymorphic_tree/icons/blank.gif
polymorphic_tree/static/polymorphic_tree/icons/page_new.gif
polymorphic_tree/static/polymorphic_tree/icons/world.gif
polymorphic_tree/static/polymorphic_tree/jqtree/LICENSE
polymorphic_tree/static/polymorphic_tree/jqtree/README.rst
polymorphic_tree/static/polymorphic_tree/jqtree/build
polymorphic_tree/static/polymorphic_tree/jqtree/build_sprite
polymorphic_tree/static/polymorphic_tree/jqtree/demo.html
polymorphic_tree/static/polymorphic_tree/jqtree/icons.png
django_polymorphic_tree_for_garpix_page-2.2.2.dist-info/METADATA
django_polymorphic_tree_for_garpix_page-2.2.2.dist-info/WHEEL
django_polymorphic_tree_for_garpix_page-2.2.2.dist-info/top_level.txt
django_polymorphic_tree_for_garpix_page-2.2.2.dist-info/RECORD
